elo_mmr_py/__init__.py
elo_mmr_py/elo_mmr_python_bindings.cpython-310-aarch64-linux-gnu.so
rust/lib.rs
test_elo_mmr_py.libs/libcrypto-3dc39733.so.1.1.1k
test_elo_mmr_py.libs/libssl-b6e07dfa.so.1.1.1k
test_elo_mmr_py-1.0.3.dist-info/METADATA
test_elo_mmr_py-1.0.3.dist-info/WHEEL
test_elo_mmr_py-1.0.3.dist-info/top_level.txt
test_elo_mmr_py-1.0.3.dist-info/RECORD
test_elo_mmr_py-1.0.3.dist-info/licenses/LICENSE
