Metadata-Version: 2.4
Name: test-elo-mmr-py
Version: 1.0.3
Summary: Python bindings for Elo-MRR
License-File: LICENSE
Dynamic: license-file
